[ {
  "ID_продажи": 1,
  "ID_продавца": 1,
  "ID_товара": 1,
  "Количество_проданных_товаров": 3,
  "Дата_продажи": "2023-11-24"
},
  {
    "ID_продажи": 2,
    "ID_продавца": 1,
    "ID_товара": 2,
    "Количество_проданных_товаров": 2,
    "Дата_продажи": "2023-11-24"
  },
  {
    "ID_продажи": 3,
    "ID_продавца": 2,
    "ID_товара": 1,
    "Количество_проданных_товаров": 5,
    "Дата_продажи": "2023-11-24"
  },
  {
    "ID_продажи": 4,
    "ID_продавца": 2,
    "ID_товара": 2,
    "Количество_проданных_товаров": 3,
    "Дата_продажи": "2023-11-22"
  },
  {
    "ID_продажи": 5,
    "ID_продавца": 3,
    "ID_товара": 1,
    "Количество_проданных_товаров": 7,
    "Дата_продажи": "2023-11-21"
  },
  {
    "ID_продажи": 6,
    "ID_продавца": 3,
    "ID_товара": 2,
    "Количество_проданных_товаров": 5,
    "Дата_продажи": "2023-11-20"
  }
]